pythonpackage_morteza/__init__.py
pythonpackage_morteza/pythonpackge_morteza.py
pythonpackage_morteza-1.0.0.dist-info/METADATA
pythonpackage_morteza-1.0.0.dist-info/WHEEL
pythonpackage_morteza-1.0.0.dist-info/top_level.txt
pythonpackage_morteza-1.0.0.dist-info/RECORD
