Metadata-Version: 2.1
Name: pythonpackage_morteza
Version: 1.0.0
Summary: A package for weight predict based on height 
Author: mori_cyber
Author-email: moridh1355@gmail.com
